{
  "generatedAt": "2026-04-22T15:36:59.197868+00:00",
  "total": 86,
  "variables": {
    "anonymousAccess": {
      "clients": {
        "sonrie-prod": false
      },
      "implemented": true
    },
    "anonymousHideCart": {
      "clients": {
        "sonrie-prod": false
      },
      "implemented": true
    },
    "anonymousHidePrice": {
      "clients": {
        "sonrie-prod": false
      },
      "implemented": true
    },
    "blockedClientAlert.enableBlockedClientAlert": {
      "clients": {
        "sonrie-prod": false
      },
      "implemented": null
    },
    "businessUnits": {
      "clients": {
        "sonrie-prod": []
      },
      "implemented": null
    },
    "commerce.enableCreateCommerce": {
      "clients": {
        "sonrie-prod": false
      },
      "implemented": false
    },
    "disableCart": {
      "clients": {
        "sonrie-prod": false
      },
      "implemented": null
    },
    "disableCommerceEdit": {
      "clients": {
        "sonrie-prod": false
      },
      "implemented": null
    },
    "disableObservationInput": {
      "clients": {
        "sonrie-prod": false
      },
      "implemented": true
    },
    "disablePayments": {
      "clients": {
        "sonrie-prod": false
      },
      "implemented": null
    },
    "disableShowEstimatedDeliveryHour": {
      "clients": {
        "sonrie-prod": false
      },
      "implemented": null
    },
    "discountTypes.discountTypesList": {
      "clients": {
        "sonrie-prod": []
      },
      "implemented": null
    },
    "discountTypes.enableOrderDiscountType": {
      "clients": {
        "sonrie-prod": false
      },
      "implemented": null
    },
    "discountTypes.enableProductDiscountType": {
      "clients": {
        "sonrie-prod": false
      },
      "implemented": null
    },
    "editAddress": {
      "clients": {
        "sonrie-prod": true
      },
      "implemented": null
    },
    "enableAskDeliveryDate": {
      "clients": {
        "sonrie-prod": false
      },
      "implemented": null
    },
    "enableBetaButtons": {
      "clients": {
        "sonrie-prod": false
      },
      "implemented": null
    },
    "enableChooseSaleUnit": {
      "clients": {
        "sonrie-prod": false
      },
      "implemented": null
    },
    "enableCoupons": {
      "clients": {
        "sonrie-prod": true
      },
      "implemented": null
    },
    "enableCreditNotes": {
      "clients": {
        "sonrie-prod": false
      },
      "implemented": null
    },
    "enableDialogNoSellReason": {
      "clients": {
        "sonrie-prod": false
      },
      "implemented": null
    },
    "enableDistributionCentersSelector": {
      "clients": {
        "sonrie-prod": false
      },
      "implemented": true
    },
    "enableInvoicesList": {
      "clients": {
        "sonrie-prod": false
      },
      "implemented": true
    },
    "enableNewUI": {
      "clients": {
        "sonrie-prod": false
      },
      "implemented": null
    },
    "enableOrderApproval": {
      "clients": {
        "sonrie-prod": false
      },
      "implemented": null
    },
    "enableOrderValidation": {
      "clients": {
        "sonrie-prod": false
      },
      "implemented": null
    },
    "enablePaymentDocumentsB2B": {
      "clients": {
        "sonrie-prod": false
      },
      "implemented": true
    },
    "enablePayments": {
      "clients": {
        "sonrie-prod": false
      },
      "implemented": null
    },
    "enablePaymentsCollection": {
      "clients": {
        "sonrie-prod": false
      },
      "implemented": null
    },
    "enablePriceOracle": {
      "clients": {
        "sonrie-prod": false
      },
      "implemented": true
    },
    "enableSellerDiscount": {
      "clients": {
        "sonrie-prod": false
      },
      "implemented": null
    },
    "enableTask": {
      "clients": {
        "sonrie-prod": false
      },
      "implemented": null
    },
    "externalAccess": {
      "clients": {
        "sonrie-prod": true
      },
      "implemented": true
    },
    "filterGroupedSuggestionsBy": {
      "clients": {
        "sonrie-prod": []
      },
      "implemented": null
    },
    "footerCustomContent.useFooterCustomContent": {
      "clients": {
        "sonrie-prod": false
      },
      "implemented": null
    },
    "hasAllDistributionCenters": {
      "clients": {
        "sonrie-prod": false
      },
      "implemented": null
    },
    "hasMultiUnitEnabled": {
      "clients": {
        "sonrie-prod": false
      },
      "implemented": true
    },
    "hasMultipleBusinessUnit": {
      "clients": {
        "sonrie-prod": false
      },
      "implemented": null
    },
    "hasNoSaleFilter": {
      "clients": {
        "sonrie-prod": false
      },
      "implemented": null
    },
    "hasSingleDistributionCenter": {
      "clients": {
        "sonrie-prod": true
      },
      "implemented": null
    },
    "hasStockEnabled": {
      "clients": {
        "sonrie-prod": false
      },
      "implemented": null
    },
    "hasTransferPaymentType": {
      "clients": {
        "sonrie-prod": false
      },
      "implemented": null
    },
    "hasTransportCode": {
      "clients": {
        "sonrie-prod": false
      },
      "implemented": null
    },
    "hasVoucherPrinterEnabled": {
      "clients": {
        "sonrie-prod": false
      },
      "implemented": null
    },
    "hidePrices": {
      "clients": {
        "sonrie-prod": false
      },
      "implemented": null
    },
    "hideReceiptType": {
      "clients": {
        "sonrie-prod": false
      },
      "implemented": null
    },
    "includeTaxRateInPrices": {
      "clients": {
        "sonrie-prod": false
      },
      "implemented": null
    },
    "lazyLoadingPrices": {
      "clients": {
        "sonrie-prod": false
      },
      "implemented": null
    },
    "limitAddingByStock": {
      "clients": {
        "sonrie-prod": false
      },
      "implemented": null
    },
    "loginButtons.facebook": {
      "clients": {
        "sonrie-prod": false
      },
      "implemented": null
    },
    "loginButtons.google": {
      "clients": {
        "sonrie-prod": false
      },
      "implemented": null
    },
    "orderPolicy.creditExceededStatus": {
      "clients": {
        "sonrie-prod": "block"
      },
      "implemented": false
    },
    "orderPolicy.retainBelowMinimumOrder": {
      "clients": {
        "sonrie-prod": false
      },
      "implemented": false
    },
    "orderPolicy.retainCreditBlockedCommerces": {
      "clients": {
        "sonrie-prod": false
      },
      "implemented": false
    },
    "ordersRequireAuthorization": {
      "clients": {
        "sonrie-prod": false
      },
      "implemented": null
    },
    "ordersRequireVerification": {
      "clients": {
        "sonrie-prod": false
      },
      "implemented": null
    },
    "packagingInformation.hidePackagingInformationB2B": {
      "clients": {
        "sonrie-prod": true
      },
      "implemented": null
    },
    "packagingInformation.hideSingleItemPackagingInformationB2B": {
      "clients": {
        "sonrie-prod": true
      },
      "implemented": null
    },
    "packagingInformation.ignoreUnitOnPackInformationB2B": {
      "clients": {
        "sonrie-prod": false
      },
      "implemented": null
    },
    "payment.balances": {
      "clients": {
        "sonrie-prod": []
      },
      "implemented": null
    },
    "payment.enableNewPaymentModule": {
      "clients": {
        "sonrie-prod": false
      },
      "implemented": null
    },
    "payment.requiresFullPayment": {
      "clients": {
        "sonrie-prod": false
      },
      "implemented": null
    },
    "paymentsWithoutAccount": {
      "clients": {
        "sonrie-prod": false
      },
      "implemented": null
    },
    "pendingDocuments": {
      "clients": {
        "sonrie-prod": false
      },
      "implemented": null
    },
    "pointsEnabled": {
      "clients": {
        "sonrie-prod": false
      },
      "implemented": null
    },
    "priceRoundingDecimals": {
      "clients": {
        "sonrie-prod": 0
      },
      "implemented": null
    },
    "productVariability": {
      "clients": {
        "sonrie-prod": "none"
      },
      "implemented": true
    },
    "purchaseOrderEnabled": {
      "clients": {
        "sonrie-prod": false
      },
      "implemented": null
    },
    "shareOrderNewDesign": {
      "clients": {
        "sonrie-prod": false
      },
      "implemented": null
    },
    "shoppingDetail.lastOrder": {
      "clients": {
        "sonrie-prod": false
      },
      "implemented": null
    },
    "showEmptyCategories": {
      "clients": {
        "sonrie-prod": false
      },
      "implemented": true
    },
    "showMinOne": {
      "clients": {
        "sonrie-prod": false
      },
      "implemented": null
    },
    "suggestions.hide": {
      "clients": {
        "sonrie-prod": true
      },
      "implemented": null
    },
    "synchronization.backgroundSyncList": {
      "clients": {
        "sonrie-prod": []
      },
      "implemented": null
    },
    "synchronization.enableBackgroundSendOrders": {
      "clients": {
        "sonrie-prod": false
      },
      "implemented": null
    },
    "synchronization.enableBackgroundSync": {
      "clients": {
        "sonrie-prod": false
      },
      "implemented": null
    },
    "synchronization.enableSyncImages": {
      "clients": {
        "sonrie-prod": false
      },
      "implemented": null
    },
    "taxes.showSummary": {
      "clients": {
        "sonrie-prod": false
      },
      "implemented": null
    },
    "taxes.taxRate": {
      "clients": {
        "sonrie-prod": 0
      },
      "implemented": null
    },
    "taxes.useTaxRate": {
      "clients": {
        "sonrie-prod": false
      },
      "implemented": true
    },
    "uploadOrderFileWithMinUnits": {
      "clients": {
        "sonrie-prod": false
      },
      "implemented": null
    },
    "useMobileGps": {
      "clients": {
        "sonrie-prod": false
      },
      "implemented": null
    },
    "useMongoPricing": {
      "clients": {
        "sonrie-prod": false
      },
      "implemented": false
    },
    "useNewPromotions": {
      "clients": {
        "sonrie-prod": false
      },
      "implemented": null
    },
    "validatePaymentFromAdmin": {
      "clients": {
        "sonrie-prod": false
      },
      "implemented": null
    },
    "weightInfo": {
      "clients": {
        "sonrie-prod": false
      },
      "implemented": null
    }
  }
}